LICENSE.GPL
LICENSE.txt
README.txt
bootstrap.py
buildout.cfg
setup.cfg
setup.py
src/collective/__init__.py
src/collective.castle.egg-info/PKG-INFO
src/collective.castle.egg-info/SOURCES.txt
src/collective.castle.egg-info/dependency_links.txt
src/collective.castle.egg-info/entry_points.txt
src/collective.castle.egg-info/namespace_packages.txt
src/collective.castle.egg-info/not-zip-safe
src/collective.castle.egg-info/requires.txt
src/collective.castle.egg-info/top_level.txt
src/collective/castle/__init__.py
src/collective/castle/browser.py
src/collective/castle/configure.zcml
src/collective/castle/control_panel.py
src/collective/castle/login_portlet.pt
src/collective/castle/portlet.py
src/collective/castle/util.py
src/collective/castle/profiles/default/actions.xml
src/collective/castle/profiles/default/controlpanel.xml
src/collective/castle/profiles/default/metadata.xml
src/collective/castle/profiles/default/portlets.xml