Metadata-Version: 1.0
Name: collective.castle
Version: 1.1
Summary: Plone UI for CAS login.
Home-page: https://svn.plone.org/svn/collective/collective.castle
Author: Derek Richardson/Plone Community
Author-email: product-developers@lists.plone.org
License: GPL
Keywords: zope plone CAS PAS
Platform: UNKNOWN
Classifier: Framework :: Plone
Classifier: Programming Language :: Python
Classifier: Topic :: Software Development :: Libraries :: Python Modules
